PandasMijiChuyiFix1/README.md
PandasMijiChuyiFix1/__init__.py
PandasMijiChuyiFix1/__main__.py
PandasMijiChuyiFix1/file.epub
PandasMijiChuyiFix1/index.html
PandasMijiChuyiFix1/css/__init__.py
PandasMijiChuyiFix1/css/annotations.css
PandasMijiChuyiFix1/css/main.css
PandasMijiChuyiFix1/css/normalize.css
PandasMijiChuyiFix1/css/popup.css
PandasMijiChuyiFix1/font/__init__.py
PandasMijiChuyiFix1/font/fontello.eot
PandasMijiChuyiFix1/font/fontello.svg
PandasMijiChuyiFix1/font/fontello.ttf
PandasMijiChuyiFix1/font/fontello.woff
PandasMijiChuyiFix1/img/__init__.py
PandasMijiChuyiFix1/img/annotator-glyph-sprite.png
PandasMijiChuyiFix1/img/annotator-icon-sprite.png
PandasMijiChuyiFix1/img/apple-touch-icon.png
PandasMijiChuyiFix1/img/cancelfullscreen.png
PandasMijiChuyiFix1/img/close.png
PandasMijiChuyiFix1/img/fullscreen.png
PandasMijiChuyiFix1/img/loader.gif
PandasMijiChuyiFix1/img/menu-icon.png
PandasMijiChuyiFix1/img/save.png
PandasMijiChuyiFix1/img/saved.png
PandasMijiChuyiFix1/img/settings-s.png
PandasMijiChuyiFix1/img/settings.png
PandasMijiChuyiFix1/img/star.png
PandasMijiChuyiFix1/js/__init__.py
PandasMijiChuyiFix1/js/epub.js
PandasMijiChuyiFix1/js/epub.min.js
PandasMijiChuyiFix1/js/epub.min.map
PandasMijiChuyiFix1/js/hooks.min.js
PandasMijiChuyiFix1/js/hooks.min.map
PandasMijiChuyiFix1/js/reader.js
PandasMijiChuyiFix1/js/reader.js.map
PandasMijiChuyiFix1/js/reader.min.js
PandasMijiChuyiFix1/js/reader.min.map
PandasMijiChuyiFix1/js/hooks/__init__.py
PandasMijiChuyiFix1/js/hooks/extensions/__init__.py
PandasMijiChuyiFix1/js/hooks/extensions/highlight.js
PandasMijiChuyiFix1/js/libs/__init__.py
PandasMijiChuyiFix1/js/libs/jquery.min.js
PandasMijiChuyiFix1/js/libs/localforage.min.js
PandasMijiChuyiFix1/js/libs/screenfull.js
PandasMijiChuyiFix1/js/libs/screenfull.min.js
PandasMijiChuyiFix1/js/libs/zip.min.js
PandasMijiChuyiFix1/js/plugins/__init__.py
PandasMijiChuyiFix1/js/plugins/hypothesis.js
PandasMijiChuyiFix1/js/plugins/search.js
pandas_miji_chuyi_fix1-2025.3.24.1.dist-info/METADATA
pandas_miji_chuyi_fix1-2025.3.24.1.dist-info/WHEEL
pandas_miji_chuyi_fix1-2025.3.24.1.dist-info/entry_points.txt
pandas_miji_chuyi_fix1-2025.3.24.1.dist-info/top_level.txt
pandas_miji_chuyi_fix1-2025.3.24.1.dist-info/RECORD
